konstantin_setup/poetry.sh
konstantin_setup/python.py
konstantin_setup/python.sh
konstantin_setup/systemd.py
konstantin_setup-0.0.2.dist-info/WHEEL
konstantin_setup-0.0.2.dist-info/METADATA
konstantin_setup-0.0.2.dist-info/RECORD
