Metadata-Version: 2.1
Name: konstantin-setup
Version: 0.0.2
Summary: Скрипты установки
Author: Konstantin-Dudersky
Author-email: Konstantin.Dudersky@gmail.com
Requires-Python: >=3.10,<4.0
Classifier: Programming Language :: Python :: 3
Classifier: Programming Language :: Python :: 3.10
